{
	"description": "项目配置文件。",
	"setting": {
		"urlCheck": false,
		"es6": true,
		"postcss": true,
		"minified": true,
		"newFeature": true
	},
	"compileType": "miniprogram",
	"libVersion": "1.6.6",
	"appid": "wx2d75876d0ca5aaff",
	"projectname": "enquiryUI",
	"condition": {
		"search": {
			"current": -1,
			"list": []
		},
		"conversation": {
			"current": -1,
			"list": []
		},
		"plugin": {
			"current": -1,
			"list": []
		},
		"game": {
			"current": -1,
			"list": []
		},
		"miniprogram": {
			"current": -1,
			"list": [
				{
					"id": 0,
					"name": "扫码",
					"pathName": "pages/personal/personal",
					"query": "scene=action%3De%26data%3Da023c147%26type%3Dea023c147%26mid%3Dea023c147",
					"scene": "1043",
					"referrerInfo": {}
				},
				{
					"id": 1,
					"name": "消息",
					"pathName": "pages/personal/personal",
					"query": "action=msg&data=&mid=3131&type=6&aid=2",
					"scene": "1014"
				},
				{
					"id": 2,
					"name": "订单",
					"pathName": "pages/personal/personal",
					"query": "action=o&data=eyJpZCI6IjE3MDI3NTYxOTI4NzE1OTczNSJ9&type=2&aid=2333&mid=321069",
					"scene": "1043",
					"referrerInfo": {}
				}
			]
		}
	}
}